2:1MUX/2:1mux.v


module mux2to1(data1, data0, sel, out);
    input data1;
    input data0;
    input sel;
    output out;
    reg out;

    always @(data0, data1, sel)
    begin
        if(!sel)
            out = data0;
        else
            out = data1; 
    end
endmodule

2:1MUX/mux_tb.v
`timescale 1ns/1ps

module tb_mux;
    reg data0;
    reg data1;
    reg sel;
    wire out;

    mux2to1 uut
    (
        .data0(data0),
        .data1(data1),
        .sel(sel),
        .out(out)
    );

    initial
    begin
        $dumpfile ("mux_out.vcd"); 
	    $dumpvars(0, tb_mux);

        data0 = 0;
        data1 = 1;
        sel = 1;

        #100

        data0 = 0; data1 = 0; sel = 1; #10;
        data0 = 0; data1 = 1; sel = 0; #10;
        data0 = 0; data1 = 1; sel = 1; #10;
        data0 = 1; data1 = 0; sel = 0; #10;
        data0 = 1; data1 = 0; sel = 1; #10;
        data0 = 1; data1 = 1; sel = 0; #10;
        data0 = 1; data1 = 1; sel = 1; #10;

    end
endmodule

2:1MUX/mux_out.vcd
$date
	Mon Apr 27 16:00:59 2020
$end
$version
	Icarus Verilog
$end
$timescale
	1ps
$end
$scope module tb_mux $end
$var wire 1 ! out $end
$var reg 1 " data0 $end
$var reg 1 # data1 $end
$var reg 1 $ sel $end
$scope module uut $end
$var wire 1 " data0 $end
$var wire 1 # data1 $end
$var wire 1 $ sel $end
$var reg 1 ! out $end
$upscope $end
$upscope $end
$enddefinitions $end
#0
$dumpvars
1$
1#
0"
1!
$end
#100000
0!
0#
#110000
0$
1#
#120000
1!
1$
#130000
0$
0#
1"
#140000
0!
1$
#150000
1!
0$
1#
#160000
1$
